OSM2PALM/OSM2PALM.py
OSM2PALM/__init__.py
OSM2PALM/__main__.py
OSM2PALM/allall.py
OSM2PALM/cal_WGSdist.py
OSM2PALM/cal_alignness.py
OSM2PALM/cal_lf.py
OSM2PALM/cal_variance.py
OSM2PALM/centroid.py
OSM2PALM/convert.py
OSM2PALM/edgeDetection.py
OSM2PALM/entropy.py
OSM2PALM/evalgeo.py
OSM2PALM/extractDomainOSM.py
OSM2PALM/geo.py
OSM2PALM/noHoles.py
OSM2PALM/rasterization.py
OSM2PALM/results.py
OSM2PALM/rotate.py
OSM2PALM/selectRegion.py
OSM2PALM/settings.py
OSM2PALM/shear.py
OSM2PALM/showDiagram.py
OSM2PALM-0.0.3.dist-info/LICENSE.txt
OSM2PALM-0.0.3.dist-info/METADATA
OSM2PALM-0.0.3.dist-info/WHEEL
OSM2PALM-0.0.3.dist-info/top_level.txt
OSM2PALM-0.0.3.dist-info/RECORD
